metadefender/__init__.py
metadefender/api.py
metadefender/app.py
metadefender/logging.py
metadefender_scan-0.2.0.dist-info/LICENSE
metadefender_scan-0.2.0.dist-info/METADATA
metadefender_scan-0.2.0.dist-info/WHEEL
metadefender_scan-0.2.0.dist-info/entry_points.txt
metadefender_scan-0.2.0.dist-info/top_level.txt
metadefender_scan-0.2.0.dist-info/RECORD
