Metadata-Version: 2.1
Name: metadefender-scan
Version: 0.2.0
Summary: Command line tool which allows to send files to MetaDefender server and fetch scanning results.
Home-page: https://github.com/mkot02/metadefender_scan
Author: mkot02
License: MIT
Classifier: Development Status :: 4 - Beta
Classifier: Environment :: Console
Classifier: Intended Audience :: System Administrators
Classifier: License :: OSI Approved :: MIT License
Classifier: Operating System :: OS Independent
Classifier: Programming Language :: Python :: 3
Classifier: Topic :: System :: Software Distribution
Requires-Python: >=3.6
License-File: LICENSE
Requires-Dist: PyYAML
Requires-Dist: requests
